[
  {
    "id": "449472_0",
    "name": "Blood Rage: Valhalla",
    "thumbnail": "https://cf.geekdo-images.com/Kl7Ozg_a4GLkwE2kg9pAzQ__thumb/img/GKfBhwTRDiz1HceXTpaobQ4dqU4=/fit-in/200x150/filters:strip_icc()/pic8967559.jpg",
    "year": "2026",
    "price": 29.96,
    "players_min": 1,
    "players_max": 6,
    "time": 33,
    "rating": 5.4,
    "minAge": 12,
    "description": "Manipulez vos adversaires dans un jeu de bluff intense.",
    "currency": "€"
  },
  {
    "id": "438442_1",
    "name": "Feya's Swamp",
    "thumbnail": "https://cf.geekdo-images.com/lxzo9PekKd4TRyBUlLH7Yw__thumb/img/1cEL93SEH6KEoO7CAlde9Sqi12s=/fit-in/200x150/filters:strip_icc()/pic8703614.png",
    "year": "2025",
    "price": 25.47,
    "players_min": 2,
    "players_max": 5,
    "time": 55,
    "rating": 7.2,
    "minAge": 10,
    "description": "Découvrez des terres inconnues avec un gameplay innovant.",
    "currency": "€"
  },
  {
    "id": "420033_2",
    "name": "Vantage",
    "thumbnail": "https://cf.geekdo-images.com/M0e9l-SHH2H4RMSAcnsDgg__thumb/img/TL_OB6SKLJpCM1u1MD4ddEAp9ic=/fit-in/200x150/filters:strip_icc()/pic8658546.jpg",
    "year": "2025",
    "price": 29.03,
    "players_min": 2,
    "players_max": 4,
    "time": 49,
    "rating": 8.14,
    "minAge": 12,
    "description": "Un jeu d'ambiance et de rapidité incontournable.",
    "currency": "€"
  },
  {
    "id": "63888_3",
    "name": "Innovation",
    "thumbnail": "https://cf.geekdo-images.com/l4fVXtRnhKMf5UPn78rEdg__thumb/img/xMh4wYMS9nA77f3KScqZsWurVgQ=/fit-in/200x150/filters:strip_icc()/pic8792317.png",
    "year": "2010",
    "price": 32.31,
    "players_min": 2,
    "players_max": 4,
    "time": 42,
    "rating": 5.89,
    "minAge": 10,
    "description": "Découvrez des terres inconnues avec un gameplay innovant.",
    "currency": "€"
  },
  {
    "id": "388367_4",
    "name": "Innovation Ultimate",
    "thumbnail": "https://cf.geekdo-images.com/n3oc3G4fIsrGwqD_i0fjTA__thumb/img/sO-dblU1r9xEcyhY4RGFD76Drqs=/fit-in/200x150/filters:strip_icc()/pic8790819.png",
    "year": "2025",
    "price": 23.43,
    "players_min": 1,
    "players_max": 6,
    "time": 63,
    "rating": 9.07,
    "minAge": 8,
    "description": "Un jeu d'ambiance et de rapidité incontournable.",
    "currency": "€"
  },
  {
    "id": "359871_5",
    "name": "Arcs",
    "thumbnail": "https://cf.geekdo-images.com/XWImAu_3RK61wbzcKboVdA__thumb/img/Ry-6KHwNgERWadyxs1X1_P3dMvY=/fit-in/200x150/filters:strip_icc()/pic8145530.png",
    "year": "2024",
    "price": 36.8,
    "players_min": 3,
    "players_max": 5,
    "time": 67,
    "rating": 9.07,
    "minAge": 8,
    "description": "Combattez pour la gloire dans des batailles mythologiques.",
    "currency": "€"
  },
  {
    "id": "418059_6",
    "name": "SETI: Search for Extraterrestrial Intelligence",
    "thumbnail": "https://cf.geekdo-images.com/_BUXOVRDU9g_eRwgpR5ZZw__thumb/img/icamIZ4nP3HHH3vczZqTr1hQgKY=/fit-in/200x150/filters:strip_icc()/pic8160466.jpg",
    "year": "2024",
    "price": 38.25,
    "players_min": 2,
    "players_max": 6,
    "time": 53,
    "rating": 7.02,
    "minAge": 12,
    "description": "Un jeu d'ambiance et de rapidité incontournable.",
    "currency": "€"
  },
  {
    "id": "436059_7",
    "name": "Nucleum: Energy Research Institute",
    "thumbnail": "https://cf.geekdo-images.com/oEBVB1mHzV9pEAze_WnaAQ__thumb/img/ztpYszEMV-XUmmFLiWZxYFvOXIU=/fit-in/200x150/filters:strip_icc()/pic8616290.jpg",
    "year": "2025",
    "price": 18.03,
    "players_min": 2,
    "players_max": 6,
    "time": 114,
    "rating": 7.83,
    "minAge": 14,
    "description": "Manipulez vos adversaires dans un jeu de bluff intense.",
    "currency": "€"
  },
  {
    "id": "436217_8",
    "name": "The Lord of the Rings: Fate of the Fellowship",
    "thumbnail": "https://cf.geekdo-images.com/scw36iBIad7l-rGzxPGcGg__thumb/img/dyMBa6SBkPwpWfA4FINqbX8RNDQ=/fit-in/200x150/filters:strip_icc()/pic8662670.png",
    "year": "2025",
    "price": 24.87,
    "players_min": 3,
    "players_max": 6,
    "time": 49,
    "rating": 8.1,
    "minAge": 12,
    "description": "Un jeu d'ambiance et de rapidité incontournable.",
    "currency": "€"
  },
  {
    "id": "342942_9",
    "name": "Ark Nova",
    "thumbnail": "https://cf.geekdo-images.com/SoU8p28Sk1s8MSvoM4N8pQ__thumb/img/4KuHNTWSMPf8vTNDKSRMMI3oOv8=/fit-in/200x150/filters:strip_icc()/pic6293412.jpg",
    "year": "2021",
    "price": 17.52,
    "players_min": 3,
    "players_max": 6,
    "time": 54,
    "rating": 9.45,
    "minAge": 10,
    "description": "Manipulez vos adversaires dans un jeu de bluff intense.",
    "currency": "€"
  },
  {
    "id": "449472_10",
    "name": "Blood Rage: Valhalla",
    "thumbnail": "https://cf.geekdo-images.com/Kl7Ozg_a4GLkwE2kg9pAzQ__thumb/img/GKfBhwTRDiz1HceXTpaobQ4dqU4=/fit-in/200x150/filters:strip_icc()/pic8967559.jpg",
    "year": "2026",
    "price": 32.33,
    "players_min": 3,
    "players_max": 6,
    "time": 90,
    "rating": 7.94,
    "minAge": 12,
    "description": "Un défi stratégique pour joueurs aguerris.",
    "currency": "€"
  },
  {
    "id": "438442_11",
    "name": "Feya's Swamp",
    "thumbnail": "https://cf.geekdo-images.com/lxzo9PekKd4TRyBUlLH7Yw__thumb/img/1cEL93SEH6KEoO7CAlde9Sqi12s=/fit-in/200x150/filters:strip_icc()/pic8703614.png",
    "year": "2025",
    "price": 38.36,
    "players_min": 2,
    "players_max": 4,
    "time": 78,
    "rating": 7.65,
    "minAge": 8,
    "description": "Manipulez vos adversaires dans un jeu de bluff intense.",
    "currency": "€"
  },
  {
    "id": "420033_12",
    "name": "Vantage",
    "thumbnail": "https://cf.geekdo-images.com/M0e9l-SHH2H4RMSAcnsDgg__thumb/img/TL_OB6SKLJpCM1u1MD4ddEAp9ic=/fit-in/200x150/filters:strip_icc()/pic8658546.jpg",
    "year": "2025",
    "price": 25.25,
    "players_min": 3,
    "players_max": 6,
    "time": 64,
    "rating": 6.76,
    "minAge": 12,
    "description": "Découvrez des terres inconnues avec un gameplay innovant.",
    "currency": "€"
  },
  {
    "id": "63888_13",
    "name": "Innovation",
    "thumbnail": "https://cf.geekdo-images.com/l4fVXtRnhKMf5UPn78rEdg__thumb/img/xMh4wYMS9nA77f3KScqZsWurVgQ=/fit-in/200x150/filters:strip_icc()/pic8792317.png",
    "year": "2010",
    "price": 31.38,
    "players_min": 2,
    "players_max": 6,
    "time": 103,
    "rating": 7.45,
    "minAge": 10,
    "description": "Un défi stratégique pour joueurs aguerris.",
    "currency": "€"
  },
  {
    "id": "388367_14",
    "name": "Innovation Ultimate",
    "thumbnail": "https://cf.geekdo-images.com/n3oc3G4fIsrGwqD_i0fjTA__thumb/img/sO-dblU1r9xEcyhY4RGFD76Drqs=/fit-in/200x150/filters:strip_icc()/pic8790819.png",
    "year": "2025",
    "price": 12.46,
    "players_min": 2,
    "players_max": 6,
    "time": 30,
    "rating": 6.66,
    "minAge": 10,
    "description": "Un jeu d’aventure immersif pour toute la famille.",
    "currency": "€"
  },
  {
    "id": "359871_15",
    "name": "Arcs",
    "thumbnail": "https://cf.geekdo-images.com/XWImAu_3RK61wbzcKboVdA__thumb/img/Ry-6KHwNgERWadyxs1X1_P3dMvY=/fit-in/200x150/filters:strip_icc()/pic8145530.png",
    "year": "2024",
    "price": 10.92,
    "players_min": 2,
    "players_max": 4,
    "time": 52,
    "rating": 7.41,
    "minAge": 8,
    "description": "Manipulez vos adversaires dans un jeu de bluff intense.",
    "currency": "€"
  },
  {
    "id": "418059_16",
    "name": "SETI: Search for Extraterrestrial Intelligence",
    "thumbnail": "https://cf.geekdo-images.com/_BUXOVRDU9g_eRwgpR5ZZw__thumb/img/icamIZ4nP3HHH3vczZqTr1hQgKY=/fit-in/200x150/filters:strip_icc()/pic8160466.jpg",
    "year": "2024",
    "price": 15.06,
    "players_min": 2,
    "players_max": 5,
    "time": 89,
    "rating": 5.33,
    "minAge": 10,
    "description": "Manipulez vos adversaires dans un jeu de bluff intense.",
    "currency": "€"
  },
  {
    "id": "436059_17",
    "name": "Nucleum: Energy Research Institute",
    "thumbnail": "https://cf.geekdo-images.com/oEBVB1mHzV9pEAze_WnaAQ__thumb/img/ztpYszEMV-XUmmFLiWZxYFvOXIU=/fit-in/200x150/filters:strip_icc()/pic8616290.jpg",
    "year": "2025",
    "price": 38.03,
    "players_min": 3,
    "players_max": 6,
    "time": 56,
    "rating": 6.72,
    "minAge": 8,
    "description": "Un jeu d'ambiance et de rapidité incontournable.",
    "currency": "€"
  },
  {
    "id": "436217_18",
    "name": "The Lord of the Rings: Fate of the Fellowship",
    "thumbnail": "https://cf.geekdo-images.com/scw36iBIad7l-rGzxPGcGg__thumb/img/dyMBa6SBkPwpWfA4FINqbX8RNDQ=/fit-in/200x150/filters:strip_icc()/pic8662670.png",
    "year": "2025",
    "price": 38.67,
    "players_min": 3,
    "players_max": 4,
    "time": 43,
    "rating": 9.27,
    "minAge": 10,
    "description": "Combattez pour la gloire dans des batailles mythologiques.",
    "currency": "€"
  },
  {
    "id": "342942_19",
    "name": "Ark Nova",
    "thumbnail": "https://cf.geekdo-images.com/SoU8p28Sk1s8MSvoM4N8pQ__thumb/img/4KuHNTWSMPf8vTNDKSRMMI3oOv8=/fit-in/200x150/filters:strip_icc()/pic6293412.jpg",
    "year": "2021",
    "price": 38.8,
    "players_min": 2,
    "players_max": 4,
    "time": 94,
    "rating": 5.13,
    "minAge": 12,
    "description": "Combattez pour la gloire dans des batailles mythologiques.",
    "currency": "€"
  },
  {
    "id": "449472_20",
    "name": "Blood Rage: Valhalla",
    "thumbnail": "https://cf.geekdo-images.com/Kl7Ozg_a4GLkwE2kg9pAzQ__thumb/img/GKfBhwTRDiz1HceXTpaobQ4dqU4=/fit-in/200x150/filters:strip_icc()/pic8967559.jpg",
    "year": "2026",
    "price": 38.72,
    "players_min": 3,
    "players_max": 4,
    "time": 101,
    "rating": 7.58,
    "minAge": 10,
    "description": "Un jeu rapide et malin, idéal pour les débutants.",
    "currency": "€"
  },
  {
    "id": "438442_21",
    "name": "Feya's Swamp",
    "thumbnail": "https://cf.geekdo-images.com/lxzo9PekKd4TRyBUlLH7Yw__thumb/img/1cEL93SEH6KEoO7CAlde9Sqi12s=/fit-in/200x150/filters:strip_icc()/pic8703614.png",
    "year": "2025",
    "price": 32.19,
    "players_min": 3,
    "players_max": 5,
    "time": 34,
    "rating": 7.25,
    "minAge": 12,
    "description": "Un jeu de coopération et d'exploration spatiale.",
    "currency": "€"
  },
  {
    "id": "420033_22",
    "name": "Vantage",
    "thumbnail": "https://cf.geekdo-images.com/M0e9l-SHH2H4RMSAcnsDgg__thumb/img/TL_OB6SKLJpCM1u1MD4ddEAp9ic=/fit-in/200x150/filters:strip_icc()/pic8658546.jpg",
    "year": "2025",
    "price": 24.01,
    "players_min": 2,
    "players_max": 4,
    "time": 69,
    "rating": 5.73,
    "minAge": 14,
    "description": "Un jeu d'ambiance et de rapidité incontournable.",
    "currency": "€"
  },
  {
    "id": "63888_23",
    "name": "Innovation",
    "thumbnail": "https://cf.geekdo-images.com/l4fVXtRnhKMf5UPn78rEdg__thumb/img/xMh4wYMS9nA77f3KScqZsWurVgQ=/fit-in/200x150/filters:strip_icc()/pic8792317.png",
    "year": "2010",
    "price": 24.95,
    "players_min": 1,
    "players_max": 4,
    "time": 62,
    "rating": 7.93,
    "minAge": 14,
    "description": "Un jeu d’aventure immersif pour toute la famille.",
    "currency": "€"
  },
  {
    "id": "388367_24",
    "name": "Innovation Ultimate",
    "thumbnail": "https://cf.geekdo-images.com/n3oc3G4fIsrGwqD_i0fjTA__thumb/img/sO-dblU1r9xEcyhY4RGFD76Drqs=/fit-in/200x150/filters:strip_icc()/pic8790819.png",
    "year": "2025",
    "price": 38.45,
    "players_min": 3,
    "players_max": 4,
    "time": 63,
    "rating": 6.78,
    "minAge": 12,
    "description": "Un défi stratégique pour joueurs aguerris.",
    "currency": "€"
  },
  {
    "id": "359871_25",
    "name": "Arcs",
    "thumbnail": "https://cf.geekdo-images.com/XWImAu_3RK61wbzcKboVdA__thumb/img/Ry-6KHwNgERWadyxs1X1_P3dMvY=/fit-in/200x150/filters:strip_icc()/pic8145530.png",
    "year": "2024",
    "price": 28.28,
    "players_min": 1,
    "players_max": 4,
    "time": 33,
    "rating": 6.78,
    "minAge": 8,
    "description": "Un jeu de coopération et d'exploration spatiale.",
    "currency": "€"
  },
  {
    "id": "418059_26",
    "name": "SETI: Search for Extraterrestrial Intelligence",
    "thumbnail": "https://cf.geekdo-images.com/_BUXOVRDU9g_eRwgpR5ZZw__thumb/img/icamIZ4nP3HHH3vczZqTr1hQgKY=/fit-in/200x150/filters:strip_icc()/pic8160466.jpg",
    "year": "2024",
    "price": 20.09,
    "players_min": 2,
    "players_max": 4,
    "time": 97,
    "rating": 9.02,
    "minAge": 14,
    "description": "Un défi stratégique pour joueurs aguerris.",
    "currency": "€"
  },
  {
    "id": "436059_27",
    "name": "Nucleum: Energy Research Institute",
    "thumbnail": "https://cf.geekdo-images.com/oEBVB1mHzV9pEAze_WnaAQ__thumb/img/ztpYszEMV-XUmmFLiWZxYFvOXIU=/fit-in/200x150/filters:strip_icc()/pic8616290.jpg",
    "year": "2025",
    "price": 35.98,
    "players_min": 2,
    "players_max": 4,
    "time": 57,
    "rating": 6.46,
    "minAge": 8,
    "description": "Découvrez des terres inconnues avec un gameplay innovant.",
    "currency": "€"
  },
  {
    "id": "436217_28",
    "name": "The Lord of the Rings: Fate of the Fellowship",
    "thumbnail": "https://cf.geekdo-images.com/scw36iBIad7l-rGzxPGcGg__thumb/img/dyMBa6SBkPwpWfA4FINqbX8RNDQ=/fit-in/200x150/filters:strip_icc()/pic8662670.png",
    "year": "2025",
    "price": 19.8,
    "players_min": 3,
    "players_max": 5,
    "time": 63,
    "rating": 9.42,
    "minAge": 12,
    "description": "Combattez pour la gloire dans des batailles mythologiques.",
    "currency": "€"
  },
  {
    "id": "342942_29",
    "name": "Ark Nova",
    "thumbnail": "https://cf.geekdo-images.com/SoU8p28Sk1s8MSvoM4N8pQ__thumb/img/4KuHNTWSMPf8vTNDKSRMMI3oOv8=/fit-in/200x150/filters:strip_icc()/pic6293412.jpg",
    "year": "2021",
    "price": 30.53,
    "players_min": 2,
    "players_max": 6,
    "time": 96,
    "rating": 9.46,
    "minAge": 14,
    "description": "Un défi stratégique pour joueurs aguerris.",
    "currency": "€"
  },
  {
    "id": "449472_30",
    "name": "Blood Rage: Valhalla",
    "thumbnail": "https://cf.geekdo-images.com/Kl7Ozg_a4GLkwE2kg9pAzQ__thumb/img/GKfBhwTRDiz1HceXTpaobQ4dqU4=/fit-in/200x150/filters:strip_icc()/pic8967559.jpg",
    "year": "2026",
    "price": 17.9,
    "players_min": 1,
    "players_max": 5,
    "time": 117,
    "rating": 6.68,
    "minAge": 10,
    "description": "Un jeu de coopération et d'exploration spatiale.",
    "currency": "€"
  },
  {
    "id": "438442_31",
    "name": "Feya's Swamp",
    "thumbnail": "https://cf.geekdo-images.com/lxzo9PekKd4TRyBUlLH7Yw__thumb/img/1cEL93SEH6KEoO7CAlde9Sqi12s=/fit-in/200x150/filters:strip_icc()/pic8703614.png",
    "year": "2025",
    "price": 35.0,
    "players_min": 3,
    "players_max": 5,
    "time": 69,
    "rating": 8.12,
    "minAge": 10,
    "description": "Découvrez des terres inconnues avec un gameplay innovant.",
    "currency": "€"
  },
  {
    "id": "420033_32",
    "name": "Vantage",
    "thumbnail": "https://cf.geekdo-images.com/M0e9l-SHH2H4RMSAcnsDgg__thumb/img/TL_OB6SKLJpCM1u1MD4ddEAp9ic=/fit-in/200x150/filters:strip_icc()/pic8658546.jpg",
    "year": "2025",
    "price": 37.92,
    "players_min": 3,
    "players_max": 5,
    "time": 95,
    "rating": 8.92,
    "minAge": 14,
    "description": "Découvrez des terres inconnues avec un gameplay innovant.",
    "currency": "€"
  },
  {
    "id": "63888_33",
    "name": "Innovation",
    "thumbnail": "https://cf.geekdo-images.com/l4fVXtRnhKMf5UPn78rEdg__thumb/img/xMh4wYMS9nA77f3KScqZsWurVgQ=/fit-in/200x150/filters:strip_icc()/pic8792317.png",
    "year": "2010",
    "price": 32.19,
    "players_min": 2,
    "players_max": 4,
    "time": 32,
    "rating": 5.08,
    "minAge": 12,
    "description": "Manipulez vos adversaires dans un jeu de bluff intense.",
    "currency": "€"
  },
  {
    "id": "388367_34",
    "name": "Innovation Ultimate",
    "thumbnail": "https://cf.geekdo-images.com/n3oc3G4fIsrGwqD_i0fjTA__thumb/img/sO-dblU1r9xEcyhY4RGFD76Drqs=/fit-in/200x150/filters:strip_icc()/pic8790819.png",
    "year": "2025",
    "price": 35.27,
    "players_min": 1,
    "players_max": 4,
    "time": 57,
    "rating": 9.27,
    "minAge": 10,
    "description": "Un classique revisité avec de nouvelles règles excitantes.",
    "currency": "€"
  },
  {
    "id": "359871_35",
    "name": "Arcs",
    "thumbnail": "https://cf.geekdo-images.com/XWImAu_3RK61wbzcKboVdA__thumb/img/Ry-6KHwNgERWadyxs1X1_P3dMvY=/fit-in/200x150/filters:strip_icc()/pic8145530.png",
    "year": "2024",
    "price": 12.75,
    "players_min": 2,
    "players_max": 4,
    "time": 94,
    "rating": 8.68,
    "minAge": 14,
    "description": "Un jeu d'ambiance et de rapidité incontournable.",
    "currency": "€"
  },
  {
    "id": "418059_36",
    "name": "SETI: Search for Extraterrestrial Intelligence",
    "thumbnail": "https://cf.geekdo-images.com/_BUXOVRDU9g_eRwgpR5ZZw__thumb/img/icamIZ4nP3HHH3vczZqTr1hQgKY=/fit-in/200x150/filters:strip_icc()/pic8160466.jpg",
    "year": "2024",
    "price": 27.26,
    "players_min": 2,
    "players_max": 4,
    "time": 52,
    "rating": 7.88,
    "minAge": 12,
    "description": "Un jeu d'ambiance et de rapidité incontournable.",
    "currency": "€"
  },
  {
    "id": "436059_37",
    "name": "Nucleum: Energy Research Institute",
    "thumbnail": "https://cf.geekdo-images.com/oEBVB1mHzV9pEAze_WnaAQ__thumb/img/ztpYszEMV-XUmmFLiWZxYFvOXIU=/fit-in/200x150/filters:strip_icc()/pic8616290.jpg",
    "year": "2025",
    "price": 36.67,
    "players_min": 2,
    "players_max": 6,
    "time": 98,
    "rating": 6.31,
    "minAge": 12,
    "description": "Combattez pour la gloire dans des batailles mythologiques.",
    "currency": "€"
  },
  {
    "id": "436217_38",
    "name": "The Lord of the Rings: Fate of the Fellowship",
    "thumbnail": "https://cf.geekdo-images.com/scw36iBIad7l-rGzxPGcGg__thumb/img/dyMBa6SBkPwpWfA4FINqbX8RNDQ=/fit-in/200x150/filters:strip_icc()/pic8662670.png",
    "year": "2025",
    "price": 19.7,
    "players_min": 3,
    "players_max": 4,
    "time": 101,
    "rating": 6.88,
    "minAge": 14,
    "description": "Un jeu d’aventure immersif pour toute la famille.",
    "currency": "€"
  },
  {
    "id": "342942_39",
    "name": "Ark Nova",
    "thumbnail": "https://cf.geekdo-images.com/SoU8p28Sk1s8MSvoM4N8pQ__thumb/img/4KuHNTWSMPf8vTNDKSRMMI3oOv8=/fit-in/200x150/filters:strip_icc()/pic6293412.jpg",
    "year": "2021",
    "price": 24.89,
    "players_min": 1,
    "players_max": 4,
    "time": 99,
    "rating": 7.68,
    "minAge": 10,
    "description": "Manipulez vos adversaires dans un jeu de bluff intense.",
    "currency": "€"
  },
  {
    "id": "449472_40",
    "name": "Blood Rage: Valhalla",
    "thumbnail": "https://cf.geekdo-images.com/Kl7Ozg_a4GLkwE2kg9pAzQ__thumb/img/GKfBhwTRDiz1HceXTpaobQ4dqU4=/fit-in/200x150/filters:strip_icc()/pic8967559.jpg",
    "year": "2026",
    "price": 25.64,
    "players_min": 2,
    "players_max": 5,
    "time": 43,
    "rating": 8.69,
    "minAge": 8,
    "description": "Combattez pour la gloire dans des batailles mythologiques.",
    "currency": "€"
  },
  {
    "id": "438442_41",
    "name": "Feya's Swamp",
    "thumbnail": "https://cf.geekdo-images.com/lxzo9PekKd4TRyBUlLH7Yw__thumb/img/1cEL93SEH6KEoO7CAlde9Sqi12s=/fit-in/200x150/filters:strip_icc()/pic8703614.png",
    "year": "2025",
    "price": 17.1,
    "players_min": 1,
    "players_max": 4,
    "time": 60,
    "rating": 6.22,
    "minAge": 10,
    "description": "Manipulez vos adversaires dans un jeu de bluff intense.",
    "currency": "€"
  },
  {
    "id": "420033_42",
    "name": "Vantage",
    "thumbnail": "https://cf.geekdo-images.com/M0e9l-SHH2H4RMSAcnsDgg__thumb/img/TL_OB6SKLJpCM1u1MD4ddEAp9ic=/fit-in/200x150/filters:strip_icc()/pic8658546.jpg",
    "year": "2025",
    "price": 16.24,
    "players_min": 2,
    "players_max": 4,
    "time": 70,
    "rating": 5.11,
    "minAge": 8,
    "description": "Un jeu de coopération et d'exploration spatiale.",
    "currency": "€"
  },
  {
    "id": "63888_43",
    "name": "Innovation",
    "thumbnail": "https://cf.geekdo-images.com/l4fVXtRnhKMf5UPn78rEdg__thumb/img/xMh4wYMS9nA77f3KScqZsWurVgQ=/fit-in/200x150/filters:strip_icc()/pic8792317.png",
    "year": "2010",
    "price": 32.18,
    "players_min": 2,
    "players_max": 5,
    "time": 62,
    "rating": 6.36,
    "minAge": 14,
    "description": "Un jeu d'ambiance et de rapidité incontournable.",
    "currency": "€"
  },
  {
    "id": "388367_44",
    "name": "Innovation Ultimate",
    "thumbnail": "https://cf.geekdo-images.com/n3oc3G4fIsrGwqD_i0fjTA__thumb/img/sO-dblU1r9xEcyhY4RGFD76Drqs=/fit-in/200x150/filters:strip_icc()/pic8790819.png",
    "year": "2025",
    "price": 29.23,
    "players_min": 1,
    "players_max": 5,
    "time": 79,
    "rating": 6.79,
    "minAge": 10,
    "description": "Parfait pour les soirées entre amis.",
    "currency": "€"
  },
  {
    "id": "359871_45",
    "name": "Arcs",
    "thumbnail": "https://cf.geekdo-images.com/XWImAu_3RK61wbzcKboVdA__thumb/img/Ry-6KHwNgERWadyxs1X1_P3dMvY=/fit-in/200x150/filters:strip_icc()/pic8145530.png",
    "year": "2024",
    "price": 37.57,
    "players_min": 2,
    "players_max": 6,
    "time": 91,
    "rating": 9.24,
    "minAge": 14,
    "description": "Combattez pour la gloire dans des batailles mythologiques.",
    "currency": "€"
  },
  {
    "id": "418059_46",
    "name": "SETI: Search for Extraterrestrial Intelligence",
    "thumbnail": "https://cf.geekdo-images.com/_BUXOVRDU9g_eRwgpR5ZZw__thumb/img/icamIZ4nP3HHH3vczZqTr1hQgKY=/fit-in/200x150/filters:strip_icc()/pic8160466.jpg",
    "year": "2024",
    "price": 25.76,
    "players_min": 2,
    "players_max": 4,
    "time": 61,
    "rating": 9.27,
    "minAge": 10,
    "description": "Découvrez des terres inconnues avec un gameplay innovant.",
    "currency": "€"
  },
  {
    "id": "436059_47",
    "name": "Nucleum: Energy Research Institute",
    "thumbnail": "https://cf.geekdo-images.com/oEBVB1mHzV9pEAze_WnaAQ__thumb/img/ztpYszEMV-XUmmFLiWZxYFvOXIU=/fit-in/200x150/filters:strip_icc()/pic8616290.jpg",
    "year": "2025",
    "price": 36.78,
    "players_min": 3,
    "players_max": 4,
    "time": 75,
    "rating": 6.95,
    "minAge": 14,
    "description": "Un jeu d’aventure immersif pour toute la famille.",
    "currency": "€"
  },
  {
    "id": "436217_48",
    "name": "The Lord of the Rings: Fate of the Fellowship",
    "thumbnail": "https://cf.geekdo-images.com/scw36iBIad7l-rGzxPGcGg__thumb/img/dyMBa6SBkPwpWfA4FINqbX8RNDQ=/fit-in/200x150/filters:strip_icc()/pic8662670.png",
    "year": "2025",
    "price": 11.1,
    "players_min": 2,
    "players_max": 4,
    "time": 79,
    "rating": 7.19,
    "minAge": 8,
    "description": "Manipulez vos adversaires dans un jeu de bluff intense.",
    "currency": "€"
  },
  {
    "id": "342942_49",
    "name": "Ark Nova",
    "thumbnail": "https://cf.geekdo-images.com/SoU8p28Sk1s8MSvoM4N8pQ__thumb/img/4KuHNTWSMPf8vTNDKSRMMI3oOv8=/fit-in/200x150/filters:strip_icc()/pic6293412.jpg",
    "year": "2021",
    "price": 16.55,
    "players_min": 2,
    "players_max": 6,
    "time": 62,
    "rating": 6.46,
    "minAge": 12,
    "description": "Combattez pour la gloire dans des batailles mythologiques.",
    "currency": "€"
  }
]